Workbook

Sheet Instructions & Scope
A1: Climate Data Maturity Matrix — Instructions and Assessment Scope
A3: Organization
A4: Assessment scope
A5: Business function or organizational unit
A6: Included teams
A7: Excluded teams
A8: Climate-information types considered
A9: Principal applications or decisions considered
A10: Assessment participants
A11: Evidence sources
A12: Assessment date
A14: How to use the matrix
A15: Purpose | B15: Use the matrix for internal reflection, dialogue, gap identification, and improvement planning. It is not an external benchmark, compliance score, or organizational ranking.
A16: Define scope | B16: Assess the whole organization only when practices are genuinely shared. Otherwise assess a clearly defined business function, unit, or major operational area and record what is included.
A17: Participate cross-functionally | B17: Include people with knowledge of relevant planning, operations, engineering, risk, climate information, data governance, and contracted work. Use Not assessed rather than guessing.
A18: Select status first | B18: Choose Implemented, In development, Not started, Not assessed, or Not applicable using the definitions below.
A19: Apply guided best fit | B19: Select the highest level substantially and consistently demonstrated. Do not select a higher level when an essential underlying capability is absent. If practice spans levels, choose the lower defensible level and explain the stronger elements.
A20: Score current practice | B20: Score only what is currently demonstrated. A blank current score is allowed when status is In development, Not started, Not assessed, or Not applicable and no level can presently be demonstrated; explain the blank in Evidence and justification.
A21: Record evidence | B21: Document evidence for the current score, mixed-level practice, blank scores, Not applicable decisions, desired maturity, and planned improvements.
A22: Set desired maturity | B22: Desired maturity is role-, risk-, and application-dependent and need not be Level 5. Consider responsibility, consequences, materiality, frequency of use, regulatory context, and access to expertise.
A23: Interpret results | B23: The criterion profile is the primary result. No overall score is calculated. Section medians are descriptive aids and must be read with ranges and status counts.
A26: Implementation status definitions
A27: Implemented | B27: The capability is currently in use within the assessment scope.
A28: In development | B28: Work is actively underway but is not yet established in normal practice.
A29: Not started | B29: The capability is relevant but no material implementation work has begun.
A30: Not assessed | B30: The assessment team lacks sufficient evidence or expertise to determine the current state.
A31: Not applicable | B31: The criterion is not relevant to the defined scope or climate-information types; provide a brief justification.

Sheet Assessment
A1: Climate Data Maturity Matrix | C1: Maturity level | H1: Assessment response
C2: Level 1 — Initial | D2: Level 2 — Developing | E2: Level 3 — Defined | F2: Level 4 — Integrated | G2: Level 5 — Adaptive | H2: Status | I2: Current maturity level | J2: Desired maturity level | K2: Evidence and justification
A4: A — Organizational Capacity, Governance and Resources | B4: A1 — Internal Climate Expertise | C4: No reliable internal source of climate expertise is available to the assessed scope; climate-related questions are handled ad hoc. | D4: One or more staff members provide informal or part-time climate support, but availability, role clarity, or continuity is limited. | E4: Designated personnel with relevant climate expertise are available and consulted for important decisions within the assessed scope. | F4: Climate expertise is embedded in or formally available to relevant functions, with clear roles, escalation pathways, and continuity arrangements. | G4: Internal expertise is sustained through succession, continuing learning, and knowledge sharing, and evolves with organizational needs and climate science.
B5: A2 — Access to External Climate Expertise | C5: No reliable relationship exists with external climate experts or service providers. | D5: External expertise is accessed occasionally for specific questions or projects, without a consistent arrangement. | E5: Appropriate external expertise can be accessed through established relationships for defined needs and projects. | F5: External experts are engaged through coordinated arrangements, with their advice documented and incorporated into relevant decisions and internal learning. | G5: External relationships are periodically evaluated and adapted to emerging needs, and support sustained knowledge transfer and appropriate co-development.
B6: A3 — Governance, Accountability and Strategic Direction | C6: No clear ownership, accountability, or strategic direction exists for climate-information use. | D6: Climate-information issues are discussed in projects or working groups, but responsibilities and decision authority remain informal or fragmented. | E6: Accountable roles, decision pathways, and organizational guidance are documented for important climate-information activities. | F6: Governance coordinates responsibilities across relevant functions and connects climate-information use to organizational risk, planning, and strategy. | G6: Governance effectiveness is reviewed and improved, with strategic direction updated as risks, evidence, responsibilities, and organizational priorities change.
B7: A4 — Financial Resources for Climate Activities | C7: No identifiable funding is available for relevant climate-information activities. | D7: Funding is obtained intermittently for individual projects, reports, or external support. | E7: Recurring funding is allocated for priority climate-information activities within the assessed scope. | F7: Funding is planned across relevant work programs and aligned with material risks, responsibilities, and investment cycles. | G7: Multi-year resource planning is reviewed and adjusted using evidence about changing needs, risks, and the effectiveness of previous investments.
B8: A5 — Staff Capacity and Time | C8: Relevant climate-information work depends on unallocated staff time or cannot be completed because capacity is unavailable. | D8: Some staff time is assigned for specific activities, but competing responsibilities regularly limit completion or continuity. | E8: Roles and expected time commitments are established for priority activities, with sufficient capacity for normal requirements. | F8: Capacity is planned across relevant functions, including coordination, technical review, oversight of contractors, and continuity during staff changes. | G8: Workload, capability needs, and delivery risks are monitored, and staffing or sourcing arrangements are adjusted proactively.
B9: A6 — Training and Professional Development | C9: No relevant training, onboarding, or learning support is available. | D9: Staff access occasional learning opportunities, but participation and continuity depend on individual initiative. | E9: Role-appropriate training or documented learning resources are available for personnel with climate-information responsibilities. | F9: Training is incorporated into onboarding and professional development for relevant roles and is refreshed periodically. | G9: Learning needs and outcomes are reviewed, and training is updated using experience, emerging methods, and changing decision requirements.
B10: A7 — Climate-Informed Reporting, Disclosures and Accountability | C10: Relevant formal outputs use climate information inconsistently or without adequate traceability and review. | D10: Climate information is included in some formal outputs, but methods, assumptions, or review practices vary. | E10: Relevant reports, disclosures, or planning outputs follow documented requirements for sources, assumptions, limitations, and internal review. | F10: Requirements are consistently applied across relevant outputs and aligned with organizational risk, planning, and accountability processes. | G10: Reporting practices are periodically evaluated and updated in response to new evidence, standards, user needs, and lessons from assurance or review.
A12: B — Climate Risk Understanding and Organizational Readiness | B12: B1 — Role-Appropriate Climate Change Understanding | C12: Relevant personnel have limited understanding of how climate variability and change relate to their responsibilities. | D12: General awareness exists, but understanding is uneven and is not consistently connected to role-specific decisions. | E12: Relevant personnel understand the principal climate implications for their roles and know when specialist advice is required. | F12: Role-appropriate understanding is established across relevant functions and is routinely applied in decisions, design, planning, or operations. | G12: Understanding is maintained and updated through continuing learning, experience, and feedback as climate evidence and organizational needs evolve.
B13: B2 — Understanding and Management of Climate-Related Risks | C13: Climate-related risks are not systematically recognized in relevant decisions. | D13: Some risks are recognized, mainly in response to events, external requests, or individual initiative. | E13: Material climate-related risks are identified and assessed for priority activities using a documented approach. | F13: Climate-related risks are incorporated into relevant organizational risk and decision processes, with clear ownership and actions for managing the risks. | G13: Risk assessments and treatments are monitored and updated as conditions, evidence, exposure, and organizational priorities change.
B14: B3 — Adaptation Readiness and Implementation | C14: Adaptation needs and responsibilities have not been identified within the assessed scope. | D14: Adaptation options are being explored, but priorities, responsibilities, or implementation pathways remain preliminary. | E14: Priority adaptation measures and responsibilities are documented, and selected measures are being implemented. | F14: Adaptation is incorporated into relevant plans, programs, or asset decisions, with implementation and outcomes monitored. | G14: Adaptation priorities, measures, and implementation plans are periodically reviewed and adjusted using observed outcomes, updated risks, and changing decision conditions.
A16: C — Planning and Deployment Strategy | B16: C1 — Alignment of Planning Horizons and Climate Information | C16: Climate-information timescales are not checked against the horizons of relevant decisions. | D16: Time horizons are considered inconsistently, and mismatches remain common or undocumented. | E16: Documented guidance links important decision types and lifecycles to appropriate climate-information timescales. | F16: Horizon alignment is consistently applied across relevant planning and operational workflows, including decisions affected by risks over multiple timescales. | G16: Horizon guidance and planning approaches are reviewed and adjusted as decision lifecycles, climate information, and risk conditions change.
B17: C2 — Use of Future Climate Information and Planning Assumptions | C17: Relevant long-term decisions rely on historical conditions or static assumptions without considering future climate change. | D17: Future climate information is considered in selected activities, but assumptions and selection rationales are informal or inconsistent. | E17: Documented future-climate assumptions, including multiple plausible futures where relevant, are used for important climate-sensitive decisions. | F17: Future climate information is systematically incorporated into relevant planning models and decisions, with assumptions coordinated and traceable. | G17: Planning assumptions and decision strategies are tested and updated as climate evidence, policies, thresholds, and observed conditions evolve.
B18: C3 — Coordination Across Relevant Teams | C18: Teams using or affected by climate information work independently with little coordination. | D18: Coordination occurs for selected projects but depends on informal relationships or individual initiative. | E18: Relevant teams use documented coordination arrangements to establish shared assumptions, responsibilities, and information needs. | F18: Established coordination arrangements connect climate-information activities across relevant functions and shared services. | G18: Coordination effectiveness is reviewed and improved, and shared practices evolve with organizational needs and lessons learned.
B19: C4 — Learning and Feedback in Climate-Information Use | C19: Outcomes and experience do not inform subsequent climate-information choices or methods. | D19: Relevant lessons are discussed after some decisions or events but are not consistently recorded or applied. | E19: Lessons from applications, decisions, forecasts, analyses, or extreme events are documented and inform later climate-information use. | F19: Feedback is built into relevant reviews and planning cycles, with responsibilities assigned for acting on identified lessons. | G19: Evidence from outcomes is systematically evaluated and used to improve data choices, assumptions, methods, tools, and decision processes.
B20: C5 — Tools and Infrastructure for Climate-Information Use | C20: Tools and storage arrangements are unreliable, undocumented, or dependent on individual workarounds. | D20: Fit-for-purpose tools exist for selected activities but are fragmented, inconsistently maintained, or weakly connected to decision workflows. | E20: Supported tools and infrastructure enable repeatable climate-information tasks for important applications. | F20: Tools are integrated into relevant organizational systems and workflows, with clear ownership, maintenance, access, and quality controls. | G20: Tool performance and user needs are monitored, and infrastructure is improved as applications, risks, and technology change.
B21: C6 — Standardized Climate-Information Practices | C21: Relevant work is ad hoc, with no agreed procedures, templates, or minimum requirements. | D21: Local checklists or templates exist, but use, ownership, and version control are inconsistent. | E21: Approved, version-controlled procedures or templates establish minimum climate-information requirements for important workflows. | F21: Applicable standards are consistently used across relevant workflows, with clear owners, review schedules, and links to relevant assumptions, methods, and supporting resources. | G21: Use and effectiveness are monitored, and standards are updated through audit findings, user feedback, lessons learned, and changing requirements.
A23: D — Data Acquisition, Provenance and Initial Screening | B23: D1 — Source Identification and Citation | C23: Data origins are unknown or inconsistently retained. | D23: Sources are recorded in some files or project notes but are not consistently linked to outputs. | E23: Source, provider, product, and version information are systematically recorded for relevant uses. | F23: Complete citations and access details are retained through relevant analyses, reports, and audit trails. | G23: Source records are maintained through governed workflows and updated when products, versions, or citation requirements change.
B24: D2 — Processing Lineage and Reproducibility | C24: Relevant transformations or adjustments cannot be reliably identified. | D24: Some processing steps are noted in files, notebooks, or scripts, but records are incomplete or difficult to reproduce. | E24: Material transformations are documented and linked to source inputs, methods, parameters, and responsible parties. | F24: Processing lineage is version-controlled and reproducible for relevant applications, including work performed by contractors where applicable. | G24: Lineage controls are maintained across workflows and improved as methods, products, providers, and audit needs change.
B25: D3 — Metadata Completeness and Management | C25: Essential metadata are missing, unreliable, or not reviewed before use. | D25: Basic metadata such as units, location, time period, and coordinate information are checked, but practices are inconsistent. | E25: Required metadata fields and conventions are documented and consistently preserved for relevant uses. | F25: Metadata completeness and conformance are routinely reviewed across relevant workflows using proportionate manual or automated checks. | G25: Metadata requirements and checks are governed and updated in response to changing products, standards, and user needs.
B26: D4 — Licensing and Usage Rights | C26: Licensing or usage conditions are unknown or not considered. | D26: Terms are recorded for some projects but are not consistently reviewed before use or sharing. | E26: Usage, sharing, attribution, and retention rights are documented and checked for relevant uses. | F26: Licensing review is incorporated into relevant acquisition, procurement, analysis, and dissemination workflows. | G26: Licensing information and controls are maintained and updated as products, uses, agreements, and requirements change.
B27: D5 — Version and Update Management | C27: Versions are not reliably identified, and different users may unknowingly use different data. | D27: Version information appears in filenames or notes, but tracking and update decisions are inconsistent. | E27: Versions are documented, inputs are retained for reproducibility, and update decisions follow an established approach. | F27: Versions and variants are linked to relevant analysis runs, outputs, and update processes across applicable workflows. | G27: Version controls, archives, and update practices are monitored and improved as products and reproducibility needs evolve.
B28: D6 — Initial Data Integrity Screening | C28: Data are used without documented checks for basic integrity or obvious problems. | D28: Users perform visual or basic checks, but the checks and responses vary by person or project. | E28: Documented screening checks relevant units, missing values, coverage, continuity, file integrity, and potentially erroneous values for relevant uses. | F28: Screening is consistently incorporated into acquisition or ingestion workflows, and findings are recorded and reviewed. | G28: Screening rules and responses are monitored and updated using recurring issues, provider information, and changing product characteristics.
A30: E — Quality Control and Validation | B30: E1 — Evaluation Against Appropriate Reference Information | C30: No meaningful comparison with appropriate reference information is undertaken where such evaluation is feasible and relevant. | D30: Selected visual or summary comparisons are made, but methods and coverage are inconsistent. | E30: Documented qualitative or quantitative evaluations are conducted for relevant variables, locations, periods, and applications. | F30: Evaluation results are consistently used in product selection, interpretation, and application across relevant workflows. | G30: Evaluation methods and reference information are reviewed and updated as products, applications, evidence, and decision needs change.
B31: E2 — Documentation of Quality-Control and Validation Procedures | C31: Quality-control and validation activities are not documented. | D31: Some steps are retained in personal notes, scripts, or project files, but documentation is incomplete or difficult to access. | E31: Procedures, methods, assumptions, and results are documented for relevant applications and are accessible to appropriate users. | F31: Documentation is version-controlled, consistently maintained, reviewed, and linked to relevant data and outputs. | G31: Documentation requirements and procedures are evaluated and improved through use, review findings, and changing technical needs.
B32: E3 — Detection, Tracking and Resolution of Data Issues | C32: Issues are frequently missed, discovered late, or resolved without a retained record. | D32: Issues are corrected case by case, and some information is retained or shared informally. | E32: Detected issues, their potential impacts, decisions, and resolutions are recorded and tracked for relevant workflows. | F32: Issue-management procedures are consistently used across relevant teams, with responsibilities, communication, and preventive actions defined. | G32: Issue patterns and responses are reviewed to prevent recurrence, improve workflows, and engage providers when upstream action is appropriate.
B33: E4 — Evaluation of Biases and Their Application Relevance | C33: Relevant biases are unknown or assumed not to affect the application. | D33: General biases are recognized, but their magnitude or implications are not consistently evaluated. | E33: Biases relevant to the variables and applications in scope are identified and documented using appropriate evidence. | F33: The consequences of relevant biases are evaluated for decisions, and suitable treatment or mitigation options are assessed. | G33: Bias evaluation and treatment are monitored and updated as data, methods, applications, and observed performance change.
B34: E5 — Evaluation of Predictive or Ensemble Product Performance | C34: Applicable products are used without evaluating predictive performance, reliability, or ensemble behaviour. | D34: Visual or qualitative performance checks are conducted, but retrospective evaluation is limited or inconsistent. | E34: Appropriate hindcast or retrospective performance metrics are documented and evaluated for relevant use cases. | F34: Performance and reliability evidence consistently informs product selection, interpretation, thresholds, and user guidance. | G34: Performance is monitored over time, and evaluation, post-processing, or use guidance is updated as products and decision needs change.
A36: F — Fitness for Purpose and Constraints | B36: F1 — Use-Case Suitability and Consideration of Alternatives | C36: Climate information is selected without a clear assessment of the intended use, decision requirements, or viable alternatives. | D36: Suitability and alternatives are considered informally, but assumptions and trade-offs are not consistently documented. | E36: Selection follows documented use-case requirements and a proportionate comparison of viable information sources or approaches. | F36: Suitability assessments are consistently reviewed with appropriate subject-matter and decision experts and inform selection across relevant applications. | G36: Selection guidance, use-case knowledge, and comparisons are maintained and improved as products, applications, and constraints change.
B37: F2 — Spatial and Temporal Coverage, Scale and Resolution | C37: Spatial or temporal characteristics are not checked against the application's requirements. | D37: Basic geographic and time alignment is considered, but representativeness, scale, or resolution mismatches remain insufficiently evaluated. | E37: Coverage, scale, granularity, resolution, and relevant processing are documented and matched to relevant use cases. | F37: Material trade-offs and limitations are evaluated with appropriate expertise and consistently reflected in application design and interpretation. | G37: Suitability criteria and mitigation approaches are reviewed and updated as information sources, applications, and decision needs evolve.
B38: F3 — Variable and Indicator Adequacy | C38: Required variables or indicators are missing, poorly defined, or used without checking their adequacy. | D38: Basic availability is checked, but completeness, definitions, dependencies, or derivation requirements are not consistently assessed. | E38: Required variables and indicators are specified and assessed for completeness, consistency, and relevance to the use cases in scope. | F38: Derived indicators and multivariable requirements are developed or selected using appropriate climate and application expertise, with definitions and methods documented. | G38: Variable and indicator requirements are evaluated and updated as applications, thresholds, evidence, and available products change.
B39: F4 — Climate Scenario and Future-Condition Alignment | C39: Future climate information is selected without considering whether scenarios, time periods, and assumptions match the decision context. | D39: Scenario suitability is considered informally, but the rationale, limitations, or relationship to the decision is incomplete. | E39: Scenario and future-condition choices are documented and matched to the decision horizon, purpose, and material uncertainties. | F39: Plausible future conditions and their implications are consistently assessed for relevant climate-sensitive decisions, using multiple futures where appropriate. | G39: Scenario choices, assumptions, and decision responses are revisited as climate evidence, policies, thresholds, and planning conditions evolve.
A41: G — Understanding and Managing Data Limitations and Uncertainty | B41: G1 — Consequences of Data Gaps and Errors | C41: Data gaps or errors are treated mainly as technical issues, without assessing their consequences for decisions or outcomes. | D41: Potential consequences are recognized for selected applications but are assessed informally or reactively. | E41: Decision points and outcomes that may be materially affected by data gaps or errors are identified and documented. | F41: Consequence assessments inform controls, contingency data, fallback procedures, and review requirements for critical workflows. | G41: Consequences and controls are monitored and updated using incidents, changing dependencies, and evolving decision risks.
B42: G2 — Methodological Assumptions and Their Implications | C42: Material assumptions in data transformations, analyses, or models are not identified or reviewed. | D42: Some assumptions are recognized, but their influence on results and decisions is not consistently traced. | E42: Material assumptions and their expected implications are documented and reviewed for relevant applications. | F42: Assumptions are linked to uncertainty sources, outputs, and decision consequences across relevant workflows. | G42: Assumptions and their implications are tested and revisited as methods, evidence, and applications change.
B43: G3 — Sensitivity of Models and Applications to Climate Inputs | C43: The influence of climate inputs on model or application outputs is not assessed. | D43: Sensitivities are understood informally or explored in isolated analyses. | E43: A documented, proportionate assessment is conducted of how climate inputs influence outputs for material applications. | F43: Sensitivity evidence consistently informs input selection, model or application configuration, thresholds, and interpretation in relevant workflows. | G43: Sensitivities and decision thresholds are monitored and retested as inputs, models, applications, and conditions change.
B44: G4 — Risks of Misuse or Misinterpretation | C44: Risks from inappropriate use or interpretation are not recognized or managed. | D44: General cautions are communicated, but application-specific misuse risks and safeguards are limited. | E44: Known misuse risks, limitations, and appropriate-use conditions are documented for relevant applications. | F44: Proportionate safeguards, review requirements, warnings, and escalation pathways are embedded in high-consequence applications. | G44: Misuse risks and safeguards are reviewed and improved using incidents, user feedback, and changing applications.
B45: G5 — Characterization of Uncertainty | C45: Material uncertainty is omitted, treated as noise, or represented without a defensible basis. | D45: Some uncertainty ranges, scenarios, or qualitative statements are produced, but the underlying sources and implications are not consistently characterized. | E45: Material uncertainty sources are identified and characterized using methods appropriate to the product and application. | F45: Uncertainty characterization is consistently linked to relevant assumptions, results, and decision consequences. | G45: Uncertainty methods and their decision use are reviewed and updated as evidence, products, and needs change.
B46: G6 — Communication and Understanding of Uncertainty | C46: Outputs are communicated deterministically or without explaining material limitations and uncertainty. | D46: Uncertainty is shown, but interpretation and implications are largely left to users. | E46: Audience-appropriate explanations communicate material limitations, uncertainty, and appropriate interpretation using consistent terminology. | F46: Communication is tailored to the decision and audience, and understanding is checked for high-consequence applications. | G46: Communication approaches are evaluated and improved using user feedback, decision experience, and changing information needs.

Sheet Summary
A1: Section Summary
A3: Section summaries are descriptive discussion aids. They do not imply that strength in one criterion compensates for weakness in another and should not be compared across materially different assessment scopes.
A5: Section | B5: Median current maturity | C5: Minimum | D5: Maximum | E5: Scored criteria | F5: Implemented | G5: In development | H5: Not started | I5: Not assessed | J5: Not applicable
A6: A — Organizational Capacity, Governance and Resources | B6: =IF(COUNT(Assessment!I4:I10)=0,"",MEDIAN(Assessment!I4:I10)) | C6: =IF(COUNT(Assessment!I4:I10)=0,"",MIN(Assessment!I4:I10)) | D6: =IF(COUNT(Assessment!I4:I10)=0,"",MAX(Assessment!I4:I10)) | E6: =COUNT(Assessment!I4:I10) -> 0 | F6: =COUNTIF(Assessment!H4:H10,"Implemented") -> 0 | G6: =COUNTIF(Assessment!H4:H10,"In development") -> 0 | H6: =COUNTIF(Assessment!H4:H10,"Not started") -> 0 | I6: =COUNTIF(Assessment!H4:H10,"Not assessed") -> 0 | J6: =COUNTIF(Assessment!H4:H10,"Not applicable") -> 0
A7: B — Climate Risk Understanding and Organizational Readiness | B7: =IF(COUNT(Assessment!I12:I14)=0,"",MEDIAN(Assessment!I12:I14)) | C7: =IF(COUNT(Assessment!I12:I14)=0,"",MIN(Assessment!I12:I14)) | D7: =IF(COUNT(Assessment!I12:I14)=0,"",MAX(Assessment!I12:I14)) | E7: =COUNT(Assessment!I12:I14) -> 0 | F7: =COUNTIF(Assessment!H12:H14,"Implemented") -> 0 | G7: =COUNTIF(Assessment!H12:H14,"In development") -> 0 | H7: =COUNTIF(Assessment!H12:H14,"Not started") -> 0 | I7: =COUNTIF(Assessment!H12:H14,"Not assessed") -> 0 | J7: =COUNTIF(Assessment!H12:H14,"Not applicable") -> 0
A8: C — Planning and Deployment Strategy | B8: =IF(COUNT(Assessment!I16:I21)=0,"",MEDIAN(Assessment!I16:I21)) | C8: =IF(COUNT(Assessment!I16:I21)=0,"",MIN(Assessment!I16:I21)) | D8: =IF(COUNT(Assessment!I16:I21)=0,"",MAX(Assessment!I16:I21)) | E8: =COUNT(Assessment!I16:I21) -> 0 | F8: =COUNTIF(Assessment!H16:H21,"Implemented") -> 0 | G8: =COUNTIF(Assessment!H16:H21,"In development") -> 0 | H8: =COUNTIF(Assessment!H16:H21,"Not started") -> 0 | I8: =COUNTIF(Assessment!H16:H21,"Not assessed") -> 0 | J8: =COUNTIF(Assessment!H16:H21,"Not applicable") -> 0
A9: D — Data Acquisition, Provenance and Initial Screening | B9: =IF(COUNT(Assessment!I23:I28)=0,"",MEDIAN(Assessment!I23:I28)) | C9: =IF(COUNT(Assessment!I23:I28)=0,"",MIN(Assessment!I23:I28)) | D9: =IF(COUNT(Assessment!I23:I28)=0,"",MAX(Assessment!I23:I28)) | E9: =COUNT(Assessment!I23:I28) -> 0 | F9: =COUNTIF(Assessment!H23:H28,"Implemented") -> 0 | G9: =COUNTIF(Assessment!H23:H28,"In development") -> 0 | H9: =COUNTIF(Assessment!H23:H28,"Not started") -> 0 | I9: =COUNTIF(Assessment!H23:H28,"Not assessed") -> 0 | J9: =COUNTIF(Assessment!H23:H28,"Not applicable") -> 0
A10: E — Quality Control and Validation | B10: =IF(COUNT(Assessment!I30:I34)=0,"",MEDIAN(Assessment!I30:I34)) | C10: =IF(COUNT(Assessment!I30:I34)=0,"",MIN(Assessment!I30:I34)) | D10: =IF(COUNT(Assessment!I30:I34)=0,"",MAX(Assessment!I30:I34)) | E10: =COUNT(Assessment!I30:I34) -> 0 | F10: =COUNTIF(Assessment!H30:H34,"Implemented") -> 0 | G10: =COUNTIF(Assessment!H30:H34,"In development") -> 0 | H10: =COUNTIF(Assessment!H30:H34,"Not started") -> 0 | I10: =COUNTIF(Assessment!H30:H34,"Not assessed") -> 0 | J10: =COUNTIF(Assessment!H30:H34,"Not applicable") -> 0
A11: F — Fitness for Purpose and Constraints | B11: =IF(COUNT(Assessment!I36:I39)=0,"",MEDIAN(Assessment!I36:I39)) | C11: =IF(COUNT(Assessment!I36:I39)=0,"",MIN(Assessment!I36:I39)) | D11: =IF(COUNT(Assessment!I36:I39)=0,"",MAX(Assessment!I36:I39)) | E11: =COUNT(Assessment!I36:I39) -> 0 | F11: =COUNTIF(Assessment!H36:H39,"Implemented") -> 0 | G11: =COUNTIF(Assessment!H36:H39,"In development") -> 0 | H11: =COUNTIF(Assessment!H36:H39,"Not started") -> 0 | I11: =COUNTIF(Assessment!H36:H39,"Not assessed") -> 0 | J11: =COUNTIF(Assessment!H36:H39,"Not applicable") -> 0
A12: G — Understanding and Managing Data Limitations and Uncertainty | B12: =IF(COUNT(Assessment!I41:I46)=0,"",MEDIAN(Assessment!I41:I46)) | C12: =IF(COUNT(Assessment!I41:I46)=0,"",MIN(Assessment!I41:I46)) | D12: =IF(COUNT(Assessment!I41:I46)=0,"",MAX(Assessment!I41:I46)) | E12: =COUNT(Assessment!I41:I46) -> 0 | F12: =COUNTIF(Assessment!H41:H46,"Implemented") -> 0 | G12: =COUNTIF(Assessment!H41:H46,"In development") -> 0 | H12: =COUNTIF(Assessment!H41:H46,"Not started") -> 0 | I12: =COUNTIF(Assessment!H41:H46,"Not assessed") -> 0 | J12: =COUNTIF(Assessment!H41:H46,"Not applicable") -> 0

Sheet Glossary
A1: Term | B1: Definition
A2: Climate information | B2: Observations, reanalyses, weather and climate forecasts, climate-model projections, derived indicators, and related analytical products used to describe past, present, or plausible future conditions.
A3: Assessment scope | B3: The organization, business function, unit, or major operational area whose current capabilities are being rated.
A4: Role-appropriate understanding | B4: The climate knowledge needed to perform a person's responsibilities, recognize material limitations or risks, and seek specialist support when required.
A5: Planning and operational activities | B5: Organizational decisions and workflows concerned with strategy, investment, design, asset management, scheduling, operation, maintenance, emergency management, or related functions; the terms do not necessarily refer to teams bearing those names.
A6: Standardization | B6: The use of approved, documented, repeatable, and maintained requirements or procedures, which may differ appropriately among products, applications, or business functions.
A7: Validation | B7: Evaluation of whether data, methods, or outputs adequately represent relevant characteristics or performance for a defined purpose, using appropriate reference information and evidence.
A8: Initial data integrity screening | B8: Basic checks for issues such as missing values, units, coordinate systems, temporal continuity, file integrity, coverage, and potentially erroneous values before substantive evaluation or use. Screening flags values for review and should not automatically treat legitimate climate extremes as errors.
A9: Predictive skill | B9: The demonstrated performance of a forecast or prediction relative to observations and an appropriate reference or baseline; it does not refer to the competence of the analyst.
A10: Climate scenario | B10: A coherent representation of possible future conditions or drivers used to explore uncertainty; a scenario is not necessarily a prediction or statement of likelihood.
A11: Guided best fit | B11: Selection of the highest maturity level substantially and consistently demonstrated, subject to essential underlying capabilities and supported by evidence.
A12: Climate mitigation | B12: Human intervention to reduce greenhouse-gas sources and emissions or enhance greenhouse-gas sinks.
... A15: External climate expertise | B15: Appropriate expertise available from sources such as climate services, consultants, research institutions, data providers, or peer organizations.
